quadruped/Correction.py
quadruped/Engine.py
quadruped/Gait.py
quadruped/Leg.py
quadruped/Servo.py
quadruped/__init__.py
quadruped/jsonFile.py
quadruped/packetDecoder.py
quadruped/version.py
quadruped-0.4.1.data/scripts/get_leg_angles.py
quadruped-0.4.1.data/scripts/get_leg_info.py
quadruped-0.4.1.dist-info/DESCRIPTION.rst
quadruped-0.4.1.dist-info/METADATA
quadruped-0.4.1.dist-info/RECORD
quadruped-0.4.1.dist-info/WHEEL
quadruped-0.4.1.dist-info/metadata.json
quadruped-0.4.1.dist-info/top_level.txt
