Metadata-Version: 2.0
Name: quadruped
Version: 0.4.1
Summary: A python robotic driver for a quadruped robot
Home-page: https://github.com/MomsFriendlyRobotCompany/quadruped
Author: Kevin Walchko
Author-email: walchko@users.noreply.github.com
License: MIT
Keywords: framework,robotic,robot,sdl2,ps4,quadruped
Platform: UNKNOWN
Classifier: Development Status :: 4 - Beta
Classifier: License :: OSI Approved :: MIT License
Classifier: Programming Language :: Python :: 2.7
Classifier: Programming Language :: Python :: 3.6
Classifier: Operating System :: Unix
Classifier: Operating System :: POSIX :: Linux
Classifier: Operating System :: MacOS :: MacOS X
Classifier: Operating System :: POSIX
Classifier: Topic :: Scientific/Engineering
Classifier: Topic :: Scientific/Engineering :: Artificial Intelligence
Classifier: Topic :: Software Development :: Libraries :: Python Modules
Requires-Dist: build-utils
Requires-Dist: mcp3208
Requires-Dist: numpy
Requires-Dist: nxp-imu
Requires-Dist: pyserial
Requires-Dist: pyxl320
Requires-Dist: simplejson
